[
  {
    "name": "华为平板广告-武侠篇",
    "post": "https://jiuselu-1257697918.cos-website.ap-guangzhou.myqcloud.com/作品截图裁剪后/华为平板广告武侠篇.png",
    "video": "https://jiuselu-1257697918.cos-website.ap-guangzhou.myqcloud.com/华为平板广告-武侠篇.mp4"
  },
  {
    "name": "华为平板广告-公交篇",
    "post": "https://jiuselu-1257697918.cos-website.ap-guangzhou.myqcloud.com/作品截图裁剪后/华为平板广告公交篇.png",
    "video": "https://jiuselu-1257697918.cos-website.ap-guangzhou.myqcloud.com/华为平板广告-公交篇.mp4"
  },
   {
    "name": "华为UBBF超宽带连接大会开场视频",
    "post": "https://jiuselu-1257697918.cos-website.ap-guangzhou.myqcloud.com/作品截图裁剪后/华为UBBF大会.png",
    "video": "https://jiuselu-1257697918.cos-website.ap-guangzhou.myqcloud.com/杭州UBBF宽带开场视频最终视频1024zxl.mp4"
  },
  {
    "name": "广东电信云总机宣传视频",
    "post": "https://jiuselu-1257697918.cos-website.ap-guangzhou.myqcloud.com/作品截图裁剪后/广东电信云总机.png",
    "video": "https://jiuselu-1257697918.cos-website.ap-guangzhou.myqcloud.com/广东电信云总ZXL中文版最终视频0628A.mp4"
  },
  {
    "name": "天乔科技宣传视频",
    "post": "https://jiuselu-1257697918.cos-website.ap-guangzhou.myqcloud.com/作品截图裁剪后/天乔科技.png",
    "video": "https://jiuselu-1257697918.cos-website.ap-guangzhou.myqcloud.com/天乔科技家居视频0821无水印中文版.mp4"
  },
  {
    "name": "华为IoT车联网宣传视频",
    "post": "https://jiuselu-1257697918.cos-website.ap-guangzhou.myqcloud.com/作品截图裁剪后/华为IoT车联网宣传视频.png",
    "video": "https://jiuselu-1257697918.cos-website.ap-guangzhou.myqcloud.com/华为IoT车联网0303无字幕版.mp4"
  },
  {
    "name": "威马汽车&即客行一家三口篇",
    "post": "https://jiuselu-1257697918.cos-website.ap-guangzhou.myqcloud.com/作品截图裁剪后/威马汽车&即客行——一家三口篇.png",
    "video": "https://jiuselu-1257697918.cos-website.ap-guangzhou.myqcloud.com/威客即客行—一家三口篇.mp4"
  },
  {
    "name": "威马汽车&即客行——兄弟篇",
    "post": "https://jiuselu-1257697918.cos-website.ap-guangzhou.myqcloud.com/作品截图裁剪后/威马汽车&即客行——兄弟篇.png",
    "video": "https://jiuselu-1257697918.cos-website.ap-guangzhou.myqcloud.com/三兄弟一分钟0118自留版.mp4"
  },
  {
    "name": "福能达饮水机京东众筹广告",
    "post": "https://jiuselu-1257697918.cos-website.ap-guangzhou.myqcloud.com/作品截图裁剪后/福能达饮水机.png",
    "video": "https://jiuselu-1257697918.cos-website.ap-guangzhou.myqcloud.com/福能达饮水机最终稿0526.mp4"
  },
  {
    "name": "沃达丰 Flying CroudCell宣传视频",
    "post": "https://jiuselu-1257697918.cos-website.ap-guangzhou.myqcloud.com/作品截图裁剪后/沃达丰 Flying CroudCell.png",
    "video": "https://jiuselu-1257697918.cos-website.ap-guangzhou.myqcloud.com/沃达丰 Flying CroudCell.mp4"
  },
  {
    "name": "华为无线方案云",
    "post": "https://jiuselu-1257697918.cos-website.ap-guangzhou.myqcloud.com/作品截图裁剪后/华为无线方案云.png",
    "video": "https://jiuselu-1257697918.cos-website.ap-guangzhou.myqcloud.com/华为无线方案云  7.13.mp4"
  },
  {
    "name": "云镜蜂巢宣传视频",
    "post": "https://jiuselu-1257697918.cos-website.ap-guangzhou.myqcloud.com/作品截图裁剪后/云镜蜂巢.png",
    "video": "https://jiuselu-1257697918.cos-website.ap-guangzhou.myqcloud.com/无锡云镜宣传片最终输出0508A.mp4"
  },
  {
    "name": "华为MTS解决方案宣传视频",
    "post": "https://jiuselu-1257697918.cos-website.ap-guangzhou.myqcloud.com/作品截图裁剪后/华为MTS.png",
    "video": "https://jiuselu-1257697918.cos-website.ap-guangzhou.myqcloud.com/华为MTS解决方案英文最终版0609.mp4"
  },
  {
    "name": "民生监管宣传视频",
    "post": "https://jiuselu-1257697918.cos-website.ap-guangzhou.myqcloud.com/作品截图裁剪后/民声监管.png",
    "video": "https://jiuselu-1257697918.cos-website.ap-guangzhou.myqcloud.com/民生监管宣传视频最终版本0808.mp4"
  },
  {
    "name": "华为网络安全实验室视频",
    "post": "https://jiuselu-1257697918.cos-website.ap-guangzhou.myqcloud.com/作品截图裁剪后/华为网络安全.png",
    "video": "https://jiuselu-1257697918.cos-website.ap-guangzhou.myqcloud.com/华为网络安全实验室视频0722.mp4"
  },
  {
    "name": "华为Home Broadband Service",
    "post": "https://jiuselu-1257697918.cos-website.ap-guangzhou.myqcloud.com/作品截图裁剪后/华为Home Broadband Service.png",
    "video": "https://jiuselu-1257697918.cos-website.ap-guangzhou.myqcloud.com/华为Home Broadband Service.mp4"
  },
  {
    "name": "华为无人机解决方案宣传片",
    "post": "https://jiuselu-1257697918.cos-website.ap-guangzhou.myqcloud.com/作品截图裁剪后/华为无人机解决方案.png",
    "video": "https://jiuselu-1257697918.cos-website.ap-guangzhou.myqcloud.com/华为无人机中文版最终版0906.mp4"
  },
  {
    "name": "华为ISP主打视频",
    "post": "https://jiuselu-1257697918.cos-website.ap-guangzhou.myqcloud.com/作品截图裁剪后/华为ISP主打视频.png",
    "video": "https://jiuselu-1257697918.cos-website.ap-guangzhou.myqcloud.com/华为ISP主打视频20170313.mp4"
  },
   {
    "name": "福永中学",
    "post": "https://jiuselu-1257697918.cos-website.ap-guangzhou.myqcloud.com/作品截图裁剪后/福永中学.png",
    "video": "https://jiuselu-1257697918.cos-website.ap-guangzhou.myqcloud.com/福永中学0919中文版.mp4"
  }
]

